{
  "kyoto": {
    "go": 441,
    "visit": 292,
    "travel": 262,
    "stay": 180,
    "get": 167,
    "head": 70,
    "see": 156,
    "train": 41,
    "leave": 93,
    "take": 230,
    "like": 128,
    "proceed": 13,
    "spend": 184,
    "do": 135,
    "arrive": 29,
    "explore": 36,
    "cover": 41,
    "move": 33,
    "continue": 17,
    "include": 31,
    "make": 61,
    "reach": 10,
    "add": 28,
    "depart": 14,
    "return": 14,
    "base": 20,
    "use": 47,
    "catch": 37,
    "check": 13,
    "enjoy": 9,
    "fly": 14,
    "focus": 10,
    "hit": 8,
    "say": 14,
    "skip": 9,
    "split": 21,
    "thank": 23,
    "transfer": 8,
    "want": 23,
    "attend": 2,
    "book": 23,
    "come": 13,
    "concentrate": 5,
    "consider": 45,
    "find": 30,
    "finish": 7,
    "give": 11,
    "need": 14,
    "pay": 6,
    "prefer": 4,
    "reduce": 6,
    "revisit": 4,
    "ride": 9,
    "send": 16,
    "stick": 3,
    "stop": 18,
    "suggest": 13,
    "tell": 3,
    "think": 6,
    "transit": 2,
    "vote": 2,
    "-spend": 1,
    "access": 4,
    "activate": 9,
    "advise": 2,
    "aim": 1,
    "allocate": 3,
    "allow": 2,
    "approach": 1,
    "arrange": 2,
    "ask": 3,
    "avoid": 8,
    "back": 1,
    "backtrack": 1,
    "bed": 1,
    "begin": 2,
    "believe": 1,
    "board": 3,
    "bottom": 1,
    "break": 3,
    "buy": 28,
    "carry": 1,
    "change": 12,
    "choose": 6,
    "climb": 1,
    "close": 2,
    "collect": 1,
    "comment": 1,
    "commute": 1,
    "complete": 1,
    "complicate": 1,
    "compress": 1,
    "compromise": 1,
    "connect": 2,
    "contact": 1,
    "contain": 1,
    "count": 1,
    "cut": 7,
    "decide": 5,
    "delay": 1,
    "deliver": 1,
    "depat": 1,
    "describe": 1,
    "discover": 1,
    "divide": 3,
    "drive": 5,
    "drop": 3,
    "eat": 3,
    "end": 6,
    "exchange": 1,
    "exclude": 1,
    "expect": 3,
    "experience": 6,
    "expire": 1,
    "express": 3,
    "extend": 3,
    "fail": 1,
    "feel": 3,
    "ferry": 1,
    "figure": 1,
    "fit": 9,
    "follow": 3,
    "forget": 2,
    "forward": 2,
    "further": 1,
    "guess": 1,
    "guide": 1,
    "happen": 2,
    "hear": 1,
    "help": 8,
    "hire": 1,
    "hope": 1,
    "imagine": 2,
    "incorporate": 1,
    "increase": 2,
    "indicate": 1,
    "inlcude": 1,
    "intend": 2,
    "japan": 2,
    "join": 1,
    "keep": 5,
    "know": 10,
    "kyoto": 1,
    "let": 3,
    "limit": 1,
    "list": 1,
    "live": 1,
    "locate": 1,
    "look": 6,
    "lose": 1,
    "love": 15,
    "maximize": 1,
    "mean": 2,
    "meet": 1,
    "mind": 1,
    "miss": 1,
    "mnt": 1,
    "navigate": 3,
    "note": 1,
    "occur": 1,
    "offer": 3,
    "ok": 3,
    "operate": 1,
    "opt": 1,
    "order": 1,
    "organise": 1,
    "overlook": 1,
    "participate": 1,
    "pass": 19,
    "peak": 1,
    "persuade": 1,
    "pick": 3,
    "place": 1,
    "plan": 6,
    "please": 3,
    "predict": 1,
    "prioritize": 1,
    "purchase": 2,
    "put": 8,
    "re-arrange": 1,
    "recommend": 25,
    "rely": 1,
    "remain": 1,
    "remark": 1,
    "remember": 1,
    "rent": 4,
    "reserve": 2,
    "resume": 1,
    "retreat": 1,
    "run": 1,
    "rush": 1,
    "sample": 1,
    "save": 9,
    "search": 2,
    "secure": 1,
    "seek": 1,
    "set": 1,
    "settle": 3,
    "shoot": 1,
    "shorten": 2,
    "show": 3,
    "sleep": 2,
    "sort": 1,
    "spare": 2,
    "specify": 1,
    "squeeze": 4,
    "stand": 2,
    "start": 17,
    "step": 1,
    "store": 1,
    "structure": 1,
    "study": 2,
    "substitute": 1,
    "swing": 1,
    "switch": 2,
    "toe": 1,
    "tour": 2,
    "track": 1,
    "trip": 1,
    "try": 8,
    "turn": 1,
    "underestimate": 1,
    "understand": 1,
    "venture": 2,
    "view": 1,
    "voice": 1,
    "wish": 1,
    "witness": 1,
    "work": 7,
    "worry": 1,
    "write": 1,
    "zip": 1
  },
  "osaka": {
    "go": 234,
    "stay": 139,
    "visit": 147,
    "fly": 189,
    "arrive": 85,
    "travel": 120,
    "depart": 26,
    "leave": 67,
    "land": 23,
    "take": 116,
    "train": 17,
    "get": 87,
    "head": 22,
    "skip": 12,
    "return": 19,
    "do": 81,
    "cover": 15,
    "explore": 17,
    "like": 36,
    "see": 49,
    "reach": 8,
    "base": 11,
    "consider": 22,
    "spend": 71,
    "come": 7,
    "end": 8,
    "make": 29,
    "proceed": 4,
    "recommend": 16,
    "start": 15,
    "use": 39,
    "arive": 2,
    "backtrack": 2,
    "book": 15,
    "buy": 22,
    "catch": 16,
    "check": 10,
    "choose": 7,
    "continue": 5,
    "cut": 6,
    "drive": 4,
    "drop": 7,
    "find": 20,
    "mean": 2,
    "move": 12,
    "need": 12,
    "pick": 6,
    "shin": 2,
    "stop": 13,
    "-leave": 1,
    "accommodate": 1,
    "activate": 3,
    "add": 9,
    "advise": 3,
    "alittle": 1,
    "allocate": 1,
    "answer": 2,
    "appreciate": 4,
    "arrange": 2,
    "assume": 1,
    "attend": 3,
    "avoid": 6,
    "begin": 2,
    "better": 1,
    "bisit": 1,
    "bother": 2,
    "break": 2,
    "bring": 1,
    "cancel": 1,
    "change": 11,
    "close": 1,
    "combine": 5,
    "commute": 2,
    "compare": 1,
    "complete": 2,
    "cost": 1,
    "deal": 1,
    "decide": 6,
    "disembark": 2,
    "distance": 1,
    "drink": 1,
    "eat": 2,
    "eliminate": 1,
    "enjoy": 4,
    "equal": 1,
    "expand": 1,
    "expect": 2,
    "express": 1,
    "extend": 1,
    "facilitate": 1,
    "fend": 1,
    "figure": 1,
    "fill": 1,
    "finish": 4,
    "finished": 1,
    "fit": 3,
    "focus": 4,
    "follow": 2,
    "forget": 1,
    "forward": 1,
    "grab": 1,
    "help": 9,
    "hit": 1,
    "impact": 1,
    "include": 11,
    "incorporate": 1,
    "intend": 1,
    "interest": 1,
    "investigate": 1,
    "japan": 3,
    "keep": 3,
    "know": 6,
    "last": 1,
    "lessen": 1,
    "let": 2,
    "limit": 1,
    "locate": 1,
    "look": 2,
    "love": 4,
    "manage": 2,
    "meet": 2,
    "mention": 1,
    "miss": 3,
    "offer": 1,
    "opt": 3,
    "pack": 1,
    "pass": 11,
    "pay": 6,
    "peak": 1,
    "plan": 4,
    "please": 4,
    "prefer": 2,
    "prioritize": 1,
    "purchase": 5,
    "put": 1,
    "rain": 1,
    "re-route": 1,
    "reconsider": 1,
    "reduce": 1,
    "relax": 1,
    "remember": 1,
    "remind": 1,
    "remove": 1,
    "rent": 1,
    "reschedule": 2,
    "research": 2,
    "reserve": 1,
    "ride": 5,
    "round": 1,
    "run": 1,
    "sacrifice": 1,
    "save": 4,
    "savor": 1,
    "say": 2,
    "scrap": 1,
    "send": 9,
    "serve": 2,
    "set": 1,
    "share": 1,
    "shellac": 1,
    "shinkansen": 1,
    "show": 2,
    "sleep": 3,
    "slot": 1,
    "sneak": 1,
    "sort": 1,
    "spare": 2,
    "split": 1,
    "squeeze": 1,
    "station": 1,
    "stick": 1,
    "stretch": 1,
    "stroll": 1,
    "study": 1,
    "suggest": 12,
    "switch": 1,
    "tell": 2,
    "thank": 17,
    "think": 5,
    "touch": 1,
    "tour": 4,
    "transfer": 5,
    "translate": 1,
    "try": 8,
    "wait": 1,
    "want": 15,
    "watch": 1,
    "we've": 1,
    "wish": 1,
    "work": 7,
    "worry": 1
  },
  "hokkaido": {
    "visit": 49,
    "go": 56,
    "stay": 8,
    "do": 11,
    "fly": 12,
    "like": 10,
    "see": 13,
    "drive": 4,
    "find": 3,
    "get": 7,
    "head": 6,
    "include": 4,
    "skip": 2,
    "add": 1,
    "advise": 3,
    "appreciate": 1,
    "arrive": 1,
    "avoid": 2,
    "book": 1,
    "catch": 2,
    "change": 2,
    "check": 1,
    "combine": 1,
    "come": 1,
    "comment": 1,
    "consider": 5,
    "contact": 1,
    "cover": 3,
    "cross": 1,
    "decide": 3,
    "drink": 1,
    "enjoy": 3,
    "experience": 1,
    "explore": 3,
    "fit": 2,
    "forget": 1,
    "forward": 1,
    "hear": 1,
    "help": 3,
    "hire": 1,
    "hurry": 1,
    "indulge": 1,
    "involve": 1,
    "jump": 1,
    "keep": 1,
    "know": 1,
    "leave": 1,
    "love": 3,
    "make": 1,
    "maximize": 1,
    "miss": 1,
    "open": 1,
    "pass": 1,
    "pick": 1,
    "place": 1,
    "plan": 1,
    "put": 1,
    "rain": 1,
    "reach": 1,
    "recheck": 1,
    "recommend": 1,
    "rent": 2,
    "reply": 1,
    "reserve": 1,
    "save": 1,
    "say": 1,
    "ski": 3,
    "spend": 15,
    "split": 1,
    "squeeze": 2,
    "start": 6,
    "structure": 1,
    "take": 9,
    "thank": 4,
    "think": 1,
    "travel": 10,
    "trek": 1,
    "try": 2,
    "use": 2,
    "view": 1,
    "want": 8,
    "witness": 1,
    "work": 1
  },
  "shinjuku": {
    "stay": 85,
    "go": 39,
    "get": 59,
    "take": 67,
    "explore": 11,
    "head": 7,
    "travel": 20,
    "check": 11,
    "make": 7,
    "return": 4,
    "drop": 4,
    "end": 3,
    "finish": 2,
    "leave": 4,
    "like": 8,
    "train": 5,
    "visit": 10,
    "walk": 2,
    "accommodate": 1,
    "advise": 1,
    "affect": 1,
    "allow": 1,
    "arrive": 13,
    "bang": 1,
    "begin": 1,
    "book": 5,
    "buy": 11,
    "cancel": 1,
    "catch": 4,
    "change": 1,
    "choose": 1,
    "consider": 4,
    "cost": 1,
    "cover": 3,
    "decide": 2,
    "depart": 2,
    "dine": 1,
    "do": 14,
    "eat": 1,
    "enjoy": 1,
    "exchange": 1,
    "figure": 2,
    "find": 6,
    "find/recognise": 1,
    "forget": 1,
    "give": 1,
    "help": 1,
    "include": 2,
    "interest": 1,
    "know": 1,
    "look": 2,
    "matter": 1,
    "move": 1,
    "navigate": 1,
    "need": 5,
    "pass": 2,
    "pay": 2,
    "pick": 2,
    "plan": 2,
    "please": 2,
    "post": 1,
    "proceed": 1,
    "purchase": 1,
    "put": 1,
    "reach": 3,
    "recommend": 4,
    "remember": 1,
    "require": 1,
    "reserve": 3,
    "ride": 3,
    "save": 1,
    "say": 1,
    "see": 7,
    "settle": 1,
    "shop": 1,
    "sit": 1,
    "spend": 12,
    "start": 1,
    "suggest": 1,
    "talk": 1,
    "tell": 2,
    "thank": 3,
    "transfer": 1,
    "transport": 1,
    "trvel": 1,
    "try": 2,
    "use": 9,
    "work": 1
  },
  "sapporo": {
    "go": 35,
    "fly": 36,
    "travel": 16,
    "visit": 7,
    "check": 2,
    "do": 8,
    "get": 13,
    "leave": 6,
    "stay": 7,
    "add": 3,
    "allow": 2,
    "appreciate": 1,
    "arrive": 4,
    "attend": 1,
    "book": 5,
    "break": 1,
    "buy": 2,
    "catch": 6,
    "close": 1,
    "consider": 5,
    "descend": 1,
    "dock": 1,
    "drive": 1,
    "drop": 2,
    "encounter": 1,
    "end": 1,
    "enjoy": 1,
    "enter": 1,
    "experience": 1,
    "find": 3,
    "happen": 1,
    "head": 2,
    "help": 1,
    "hv": 1,
    "include": 2,
    "involve": 1,
    "know": 2,
    "kyoto": 1,
    "land": 2,
    "like": 4,
    "look": 2,
    "make": 2,
    "move": 2,
    "need": 1,
    "neeed": 1,
    "note": 1,
    "occur": 1,
    "organise": 1,
    "pass": 2,
    "prefer": 2,
    "proceed": 1,
    "reach": 1,
    "recommend": 2,
    "rent": 2,
    "return": 3,
    "say": 1,
    "see": 3,
    "seem": 1,
    "ski": 2,
    "spare": 1,
    "spend": 4,
    "start": 4,
    "stop": 1,
    "suggest": 1,
    "take": 11,
    "thank": 1,
    "train": 2,
    "transfer": 3,
    "try": 2,
    "use": 3,
    "want": 4,
    "watch": 1,
    "work": 4
  },
  "kobe": {
    "visit": 31,
    "go": 30,
    "stay": 11,
    "get": 9,
    "make": 4,
    "see": 9,
    "do": 7,
    "offer": 4,
    "spend": 9,
    "stop": 5,
    "take": 9,
    "travel": 10,
    "try": 4,
    "use": 4,
    "add": 3,
    "arrive": 2,
    "attend": 1,
    "bother": 1,
    "buy": 1,
    "change": 1,
    "check": 1,
    "close": 1,
    "combine": 1,
    "come": 1,
    "commute": 1,
    "consider": 2,
    "continue": 1,
    "drop": 1,
    "eat": 2,
    "explain": 1,
    "explore": 3,
    "figure": 1,
    "fly": 3,
    "happen": 1,
    "head": 1,
    "include": 1,
    "know": 2,
    "leave": 1,
    "like": 3,
    "love": 1,
    "meet": 2,
    "miss": 1,
    "need": 2,
    "omit": 1,
    "pass": 1,
    "pay": 1,
    "prefer": 1,
    "proceed": 1,
    "provide": 1,
    "put": 2,
    "recommend": 1,
    "research": 1,
    "return": 1,
    "settle": 1,
    "squeeze": 1,
    "start": 1,
    "station": 1,
    "thank": 2,
    "think": 1,
    "throw": 1,
    "train": 1,
    "transfer": 1,
    "transport": 1,
    "wait": 1,
    "want": 1
  },
  "thailand": {
    "say": 12,
    "go": 5,
    "catch": 1,
    "cost": 1,
    "find": 1,
    "head": 1,
    "jump": 1,
    "know": 1,
    "leave": 1,
    "pay": 1,
    "relax": 1,
    "return": 1,
    "see": 1,
    "shanghai": 1,
    "skip": 1,
    "spend": 1,
    "try": 1,
    "visit": 1
  },
  "yokohama": {
    "go": 24,
    "visit": 22,
    "stay": 16,
    "travel": 6,
    "get": 6,
    "include": 2,
    "like": 5,
    "stop": 3,
    "take": 15,
    "allow": 1,
    "arrive": 1,
    "attend": 1,
    "base": 1,
    "bother": 1,
    "catch": 1,
    "check": 1,
    "coincide": 1,
    "combine": 2,
    "come": 1,
    "consider": 3,
    "cover": 1,
    "cruise": 1,
    "decide": 1,
    "depart": 1,
    "do": 8,
    "drink": 1,
    "drop": 1,
    "explore": 3,
    "fill": 1,
    "find": 2,
    "finish": 1,
    "fit": 2,
    "head": 1,
    "help": 1,
    "join": 1,
    "leave": 3,
    "live": 1,
    "look": 1,
    "make": 3,
    "need": 2,
    "note": 1,
    "ok": 1,
    "pass": 1,
    "pay": 1,
    "plan": 1,
    "reach": 2,
    "recommend": 2,
    "regard": 1,
    "rent": 1,
    "return": 2,
    "save": 1,
    "say": 1,
    "see": 6,
    "seem": 1,
    "send": 2,
    "sightsee": 1,
    "spare": 1,
    "spend": 4,
    "stick": 1,
    "swap": 1,
    "thank": 3,
    "think": 1,
    "train": 2,
    "transit": 1,
    "try": 1,
    "use": 1,
    "want": 1
  },
  "fukuoka": {
    "go": 13,
    "arrive": 9,
    "travel": 7,
    "visit": 7,
    "fly": 12,
    "get": 12,
    "train": 5,
    "call": 2,
    "explore": 2,
    "head": 7,
    "proceed": 2,
    "start": 3,
    "stay": 4,
    "take": 11,
    "thank": 4,
    "avoid": 1,
    "base": 1,
    "book": 3,
    "buy": 2,
    "cancel": 1,
    "choose": 1,
    "close": 1,
    "consider": 3,
    "cover": 1,
    "decide": 1,
    "depart": 1,
    "do": 7,
    "eat": 2,
    "end": 2,
    "enjoy": 1,
    "ferry": 1,
    "finalize": 1,
    "fit": 1,
    "hire": 1,
    "include": 1,
    "know": 1,
    "land": 1,
    "leave": 4,
    "like": 2,
    "loop": 1,
    "make": 1,
    "mean": 1,
    "meet": 1,
    "move": 2,
    "name": 1,
    "need": 1,
    "pay": 1,
    "pick": 1,
    "provide": 1,
    "recommend": 1,
    "rent": 1,
    "return": 1,
    "ride": 2,
    "round": 1,
    "save": 1,
    "say": 1,
    "see": 2,
    "spare": 1,
    "speak": 1,
    "spend": 4,
    "split": 1,
    "stop": 1,
    "trek": 1,
    "try": 2,
    "turn": 1,
    "use": 3,
    "work": 2,
    "worth": 1
  },
  "tohoku": {
    "go": 11,
    "explore": 6,
    "visit": 7,
    "combine": 1,
    "commence": 1,
    "consider": 2,
    "cover": 1,
    "discourage": 1,
    "do": 4,
    "enjoy": 1,
    "expand": 1,
    "extend": 1,
    "find": 1,
    "fly": 1,
    "head": 1,
    "help": 2,
    "include": 1,
    "leave": 1,
    "mean": 1,
    "need": 1,
    "pass": 1,
    "reccommend": 1,
    "see": 6,
    "start": 2,
    "stop": 1,
    "suggest": 1,
    "thank": 1,
    "travel": 2,
    "try": 1,
    "venture": 2,
    "want": 1
  },
  "shibuya": {
    "visit": 20,
    "explore": 13,
    "get": 12,
    "go": 13,
    "stay": 10,
    "recommend": 4,
    "see": 9,
    "access": 1,
    "add": 2,
    "answer": 1,
    "arrive": 3,
    "avoid": 1,
    "catch": 1,
    "check": 2,
    "choose": 3,
    "close": 1,
    "congregate": 2,
    "consider": 6,
    "decide": 1,
    "dine": 1,
    "do": 7,
    "extend": 1,
    "feel": 1,
    "find": 3,
    "fly": 1,
    "help": 1,
    "include": 1,
    "interest": 1,
    "leave": 2,
    "like": 2,
    "look": 2,
    "love": 1,
    "lunch": 1,
    "make": 2,
    "mean": 1,
    "merge": 1,
    "prob": 1,
    "reach": 2,
    "rent": 1,
    "send": 1,
    "shop": 1,
    "side": 1,
    "spend": 1,
    "start": 3,
    "stick": 1,
    "stroll": 1,
    "suggest": 1,
    "take": 9,
    "taxi": 1,
    "thank": 1,
    "train": 1,
    "travel": 2,
    "try": 1,
    "walk": 5,
    "wrap": 1
  },
  "seoul": {
    "fly": 12,
    "travel": 3,
    "visit": 2,
    "arrive": 2,
    "check": 1,
    "do": 1,
    "end": 1,
    "expire": 1,
    "get": 2,
    "go": 3,
    "include": 1,
    "leave": 1,
    "like": 1,
    "love": 1,
    "make": 2,
    "pick": 1,
    "provide": 1,
    "see": 1,
    "skip": 1,
    "start": 1,
    "stay": 1,
    "try": 1,
    "want": 1
  },
  "shikoku": {
    "go": 13,
    "consider": 2,
    "get": 2,
    "like": 2,
    "visit": 4,
    "add": 1,
    "avoid": 1,
    "choose": 1,
    "cross": 2,
    "do": 1,
    "drive": 1,
    "explore": 2,
    "extend": 1,
    "head": 3,
    "hit": 1,
    "know": 1,
    "move": 1,
    "pick": 1,
    "plan": 1,
    "recommend": 2,
    "rent": 1,
    "ride": 1,
    "see": 7,
    "spend": 4,
    "tour": 1,
    "travel": 1,
    "try": 1,
    "want": 1
  },
  "shinagawa": {
    "change": 6,
    "reach": 3,
    "get": 9,
    "go": 13,
    "stop": 2,
    "take": 28,
    "alight": 1,
    "arrive": 1,
    "board": 1,
    "book": 1,
    "catch": 3,
    "check": 2,
    "come": 1,
    "consider": 4,
    "do": 1,
    "express": 1,
    "find": 1,
    "guide": 1,
    "head": 1,
    "help": 1,
    "imagine": 1,
    "involve": 1,
    "keep": 1,
    "lug": 1,
    "make": 1,
    "need": 2,
    "reserve": 1,
    "ride": 1,
    "see": 1,
    "specify": 1,
    "stay": 5,
    "store": 1,
    "suggest": 1,
    "thank": 1,
    "transfer": 4,
    "transit": 1,
    "travel": 2,
    "try": 1
  },
  "nyc": {
    "advise": 2,
    "compare": 1,
    "fly": 3,
    "help": 1,
    "leave": 1,
    "pick": 1,
    "see": 1,
    "stay": 1,
    "think": 1,
    "visit": 1
  },
  "chugoku": {
    "explore": 2,
    "gaze": 1,
    "go": 1,
    "leave": 1,
    "like": 1,
    "see": 2,
    "spend": 1,
    "wander": 1
  },
  "brisbane": {
    "fly": 3,
    "buy": 1,
    "depart": 1,
    "go": 2,
    "pass": 1,
    "want": 1
  },
  "toronto": {
    "fly": 2,
    "arrive": 1,
    "book": 1,
    "buy": 1,
    "depart": 1,
    "get": 1,
    "please": 1
  },
  "bangkok": {
    "fly": 3,
    "depart": 1,
    "go": 3,
    "stay": 1,
    "travel": 2,
    "try": 1,
    "visit": 1
  },
  "beijing": {
    "fly": 2,
    "arrive": 1,
    "depart": 1,
    "determine": 1,
    "do": 1,
    "drop": 1,
    "get": 2,
    "go": 1,
    "japan": 1,
    "parallel": 1,
    "see": 2,
    "stay": 1,
    "take": 1,
    "thank": 1,
    "train": 1,
    "visit": 1
  },
  "chubu": {
    "get": 2,
    "bring": 1,
    "choose": 1,
    "cover": 1,
    "depart": 1,
    "do": 2,
    "go": 3,
    "head": 1,
    "include": 1,
    "spend": 3,
    "use": 1,
    "visit": 1
  },
  "cambodia": { "go": 3, "visit": 1 },
  "germany": { "go": 2, "arrange": 1, "pay": 1, "tour": 1 },
  "maldive": { "go": 2 },
  "florida": { "leave": 2, "depart": 1, "hate": 1 },
  "taiwan": {
    "like": 2,
    "buy": 1,
    "cross": 1,
    "explore": 1,
    "fly": 1,
    "go": 1,
    "plan": 1,
    "take": 1,
    "try": 1,
    "visit": 1
  },
  "philippine": { "return": 2, "go": 1, "head": 1, "send": 1, "use": 1 },
  "asia": {
    "spend": 2,
    "adjust": 1,
    "book": 1,
    "buy": 1,
    "check": 1,
    "do": 2,
    "find": 2,
    "go": 3,
    "know": 1,
    "like": 2,
    "love": 1,
    "plan": 1,
    "see": 2,
    "take": 1,
    "thank": 1,
    "think": 1,
    "tour": 1,
    "travel": 3,
    "visit": 2
  },
  "chuo": { "take": 3, "catch": 1, "expect": 1, "get": 1, "ride": 1, "see": 1 },
  "kanto": {
    "advise": 1,
    "cover": 2,
    "do": 2,
    "find": 1,
    "focus": 2,
    "help": 1,
    "like": 2,
    "recommend": 2,
    "schedule": 1,
    "scroll": 1,
    "see": 1,
    "spare": 1,
    "spend": 4,
    "stay": 1,
    "stick": 1,
    "travel": 4,
    "use": 2,
    "visit": 2
  },
  "boston": { "arrive": 1, "book": 1, "bring": 1, "fly": 3, "see": 1 },
  "hanoi": { "arrive": 1, "catch": 1 },
  "malaysia": {
    "arrive": 1,
    "assist": 1,
    "buy": 1,
    "expect": 1,
    "know": 1,
    "note": 1,
    "purchase": 1,
    "receive": 1,
    "recommend": 1,
    "resemble": 1,
    "snow": 1,
    "take": 1,
    "visit": 2,
    "want": 1
  },
  "la": {
    "arrive": 1,
    "buy": 1,
    "fly": 2,
    "get": 1,
    "imagine": 1,
    "need": 1,
    "pack": 1,
    "see": 1
  },
  "paris": {
    "beware": 1,
    "get": 2,
    "go": 1,
    "like": 1,
    "live": 1,
    "send": 1,
    "stay": 1,
    "travel": 1
  },
  "alaska": { "bone": 1 },
  "oslo": { "book": 1 },
  "honolulu": { "book": 1, "call": 1, "fly": 2, "transit": 1 },
  "vancouver": { "book": 1 },
  "kinki": { "book": 1, "stay": 1 },
  "scotland": { "bring": 1, "take": 1, "use": 1 },
  "indonesia": { "buy": 1, "go": 1, "meet": 1, "spend": 1, "take": 1 },
  "poland": { "buy": 1, "deliver": 1 },
  "egypt": { "buy": 1 },
  "belgium": { "buy": 1, "get": 2 },
  "azerbaijan": { "call": 1 },
  "manila": {
    "catch": 1,
    "complain": 1,
    "fly": 3,
    "get": 1,
    "leave": 1,
    "route": 1,
    "take": 1
  },
  "bali": { "change": 1, "combine": 1, "do": 1 },
  "mongolia": { "choose": 1 },
  "shanghai": {
    "compare": 1,
    "fly": 4,
    "get": 2,
    "go": 1,
    "see": 1,
    "take": 1,
    "thank": 1,
    "travel": 1
  },
  "istanbul": { "compete": 1, "mention": 1 },
  "norway": { "complete": 1, "find": 1, "get": 1 },
  "frankfurt": { "connect": 1 },
  "charleston": { "consider": 1 },
  "tanzania": { "consider": 1 },
  "bahrain": { "consult": 1 },
  "melbourne": {
    "contact": 1,
    "find": 1,
    "fly": 2,
    "get": 1,
    "help": 1,
    "pack": 1,
    "travel": 1
  },
  "austria": { "contact": 1 },
  "dubai": { "cover": 1, "do": 1, "fly": 2, "get": 1, "go": 1, "know": 1 },
  "fiji": { "decide": 1, "know": 2, "see": 1, "start": 1, "stay": 1 },
  "minato": {
    "decide": 1,
    "go": 1,
    "need": 1,
    "recommend": 1,
    "spend": 1,
    "stay": 1
  },
  "auckland": { "depart": 1 },
  "ireland": { "depart": 1, "explore": 1, "fly": 1, "get": 2, "go": 1 },
  "manchester": { "do": 1, "fly": 2 },
  "sumida": { "do": 1, "explore": 1, "see": 1 },
  "guam": { "escape": 1, "get": 1, "pick": 1, "prefer": 1, "travel": 1 },
  "venice": { "expect": 1, "go": 1 },
  "montreal": { "find": 1 },
  "amsterdam": { "fly": 2, "shop": 1 },
  "dublin": { "fly": 1 },
  "bolivia": { "fly": 1 },
  "taipei": { "fly": 1, "travel": 1 },
  "changi": { "fly": 1, "rent": 1 },
  "seattle": { "fly": 1, "leave": 1, "travel": 1 },
  "caribbean": { "fly": 1 },
  "peru": { "follow": 1 },
  "washington": { "get": 1, "reach": 1 },
  "penang": { "go": 1 },
  "liverpool": { "go": 1 },
  "laos": { "go": 1, "make": 1 },
  "chile": { "go": 1, "overcome": 1 },
  "orlando": { "go": 1, "visit": 1 },
  "taito": { "go": 1, "like": 1, "recommend": 1, "stay": 2 },
  "wales": { "handle": 1, "seem": 1 },
  "qatar": { "help": 1 },
  "kuwait": { "japan": 1 },
  "baltimore": { "leave": 1 },
  "atlanta": { "leave": 1, "make": 1 },
  "queensland": { "leave": 1, "seem": 1 },
  "setagaya": { "live": 1, "see": 2 },
  "phuket": { "make": 1, "stay": 1, "travel": 1 },
  "israel": { "need": 1 },
  "jakarta": { "obtain": 1, "take": 1 },
  "nepal": { "organize": 1 },
  "vienna": { "pass": 1 },
  "iceland": { "plan": 1 },
  "moscow": { "post": 1 },
  "brazil": { "search": 1 },
  "madagascar": { "see": 1 },
  "south": { "see": 1 },
  "tibet": { "see": 1 },
  "ontario": { "see": 1 },
  "spain": { "see": 1 },
  "chiyoda": { "see": 1, "stay": 1, "travel": 1 },
  "monterey": { "see": 1 },
  "ohio": { "sound": 1 },
  "koto": { "spend": 1 },
  "panama": { "take": 1 },
  "argentina": { "thank": 1 },
  "stockholm": { "travel": 1 },
  "hong-kong": { "travel": 1 },
  "ladakh": { "visit": 1 },
  "prague": { "visit": 1 },
  "undefined": { "undefined": null }
}
